{
	"name": "API_Connection",
	"properties": {
		"linkedServiceName": {
			"referenceName": "IEX Cloud",
			"type": "LinkedServiceReference"
		},
		"parameters": {
			"Symbol": {
				"type": "string",
				"defaultValue": "ADBE"
			},
			"Token": {
				"type": "string",
				"defaultValue": "@pipeline().parameters.token"
			}
		},
		"annotations": [],
		"type": "RestResource",
		"typeProperties": {
			"relativeUrl": {
				"value": "@concat('CORE/COMPANY/',dataset().Symbol,'?token=',dataset().Token)",
				"type": "Expression"
			}
		},
		"schema": []
	}
}